Workbook

Sheet Eicher Motors IS
B3: Eicher Motors - Consolidated Income Statement ('INR Crore) | I3: Eicher Motors - Common Size Income Statement
C4: Consolidated Income Statement | D4: March 31, 2025 | E4: March 31, 2024 | F4: March 31, 2023 | G4: March 31, 2022 | I4: Consolidated Income Statement | J4: March 31, 2025 | K4: March 31, 2024 | L4: March 31, 2023 | M4: March 31, 2022
B5: Revenue or Sales | C5: Revenue from Operations | D5: 18870.35 | E5: 16535.78 | F5: 14442.18 | G5: 10297.83 | I5: Total Revenue or Income | J5: 20175.25 | K5: 17611.65 | L5: 15037.29 | M5: 10738.65
C6: Other Income | D6: 1304.9 | E6: 1075.87 | F6: 595.11 | G6: 440.82 | I6: Cost of Raw Material and Components Consumed | J6: =D8/J5 -> 0.49333515 | K6: =E8/K5 -> 0.49530283 | L6: =F8/L5 -> 0.52163322 | M6: =G8/M5 -> 0.53686823
C7: Total Revenue or Income | D7: =D5+D6 -> 20175.25 | E7: =E5+E6 -> 17611.65 | F7: =F5+F6 -> 15037.29 | G7: =G5+G6 -> 10738.65 | I7: Purchases of Traded Goods | J7: =D9/J5 -> 0.025151113 | K7: =E9/K5 -> 0.025811324 | L7: =F9/L5 -> 0.02867538 | M7: =G9/M5 -> 0.031571008
B8: Cost Of Goods Sold (COGS) | C8: Cost of Raw Material and Components Consumed | D8: 9953.16 | E8: 8723.1 | F8: 7843.95 | G8: 5765.24 | I8: Total COGS | J8: =D11/J5 -> 0.51038178 | K8: =E11/K5 -> 0.50992667 | L8: =F11/L5 -> 0.54610239 | M8: =G11/M5 -> 0.5546023
C9: Purchases of Traded Goods | D9: 507.43 | E9: 454.58 | F9: 431.2 | G9: 339.03 | I9: Gross Profit | J9: =D12/J5 -> 0.48961822 | K9: =E12/K5 -> 0.49007333 | L9: =F12/L5 -> 0.45389761 | M9: =G12/M5 -> 0.4453977
C10: Change in Inventories of Finished Goods, work-in-progress and Traded Goods | D10: -163.51 | E10: -197.03 | F10: -63.25 | G10: -148.59 | I10: Employee Benefits Expense | J10: =D14/J5 -> 0.068957262 | K10: =E14/K5 -> 0.070163216 | L10: =F14/L5 -> 0.066629692 | M10: =G14/M5 -> 0.076454675
C11: Total COGS | D11: =SUM(D8:D10) -> 10297.08 | E11: =SUM(E8:E10) -> 8980.65 | F11: =SUM(F8:F10) -> 8211.9 | G11: =SUM(G8:G10) -> 5955.68 | I11: Depreciation and Amortisation Expense | J11: =D15/J5 -> 0.036149738 | K11: =E15/K5 -> 0.033932085 | L11: =F15/L5 -> 0.034993672 | M11: =G15/M5 -> 0.042084433
B12: Revenue - COGS | C12: Gross Profit | D12: =D7-D11 -> 9878.17 | E12: =E7-E11 -> 8631 | F12: =F7-F11 -> 6825.39 | G12: =G7-G11 -> 4782.97 | I12: Other Expenses | J12: =D16/J5 -> 0.12242773 | K12: =E16/K5 -> 0.11313704 | L12: =F16/L5 -> 0.1186896 | M12: =G16/M5 -> 0.12560983
I13: Total OPEX | J13: =D17/J5 -> 0.22753473 | K13: =E17/K5 -> 0.21723234 | L13: =F17/L5 -> 0.22031297 | M13: =G17/M5 -> 0.24414894
B14: Operating Expenses (OPEX) | C14: Employee Benefits Expense | D14: 1391.23 | E14: 1235.69 | F14: 1001.93 | G14: 821.02 | I14: Operating Profit or Earnings Before Interest and Taxes (EBIT) | J14: =D18/J5 -> 0.26208349 | K14: =E18/K5 -> 0.27284099 | L14: =F18/L5 -> 0.23358464 | M14: =G18/M5 -> 0.20124876
C15: Depreciation and Amortisation Expense | D15: 729.33 | E15: 597.6 | F15: 526.21 | G15: 451.93 | I15: Finance Costs | J15: =D20/J5 -> 0.0026933991 | K15: =E20/K5 -> 0.0028889968 | L15: =F20/L5 -> 0.0018633677 | M15: =G20/M5 -> 0.0017488232
C16: Other Expenses | D16: 2470.01 | E16: 1992.53 | F16: 1784.77 | G16: 1348.88 | I16: Share of Profit of Joint Venture (VE Commercial Vehicles Limited) | J16: =D21/J5 -> 0.034686559 | K16: =E21/K5 -> 0.025421809 | L16: =F21/L5 -> 0.020959229 | M16: =G21/M5 -> 0.0056012627
C17: Total OPEX | D17: =D14+D15+D16 -> 4590.57 | E17: =E14+E15+E16 -> 3825.82 | F17: =F14+F15+F16 -> 3312.91 | G17: =G14+G15+G16 -> 2621.83 | I17: Profit Before Tax (PBT) | J17: =D22/J5 -> 0.29407665 | K17: =E22/K5 -> 0.2953738 | L17: =F22/L5 -> 0.2526805 | M17: =G22/M5 -> 0.2051012
B18: Gross Profit - OPEX | C18: Operating Profit or Earnings Before Interest and Taxes (EBIT) | D18: =D12-D17 -> 5287.6 | E18: =E12-E17 -> 4805.18 | F18: =F12-F17 -> 3512.48 | G18: =G12-G17 -> 2161.14 | I18: Current Tax | J18: =D24/J5 -> 0.055540328 | K18: =E24/K5 -> 0.059056363 | L18: =F24/L5 -> 0.054473246 | M18: =G24/M5 -> 0.048555452
I19: Deferred tax | J19: =D25/J5 -> 0.003870584 | K19: =E25/K5 -> 0.0091377015 | L19: =F25/L5 -> 0.0044263295 | M19: =G25/M5 -> 0.00041811587
B20: Interest | C20: Finance Costs | D20: 54.34 | E20: 50.88 | F20: 28.02 | G20: 18.78 | I20: Total Tax Expense | J20: =D26/J5 -> 0.059410912 | K20: =E26/K5 -> 0.068194065 | L20: =F26/L5 -> 0.058899576 | M20: =G26/M5 -> 0.048973567
B21: Non-Operating Income | C21: Share of Profit of Joint Venture (VE Commercial Vehicles Limited) | D21: 699.81 | E21: 447.72 | F21: 315.17 | G21: 60.15 | I21: Net Income or Proft After Tax (PAT) | J21: =D27/J5 -> 0.23466574 | K21: =E27/K5 -> 0.22717974 | L21: =F27/L5 -> 0.19378093 | M21: =G27/M5 -> 0.15612763
B22: EBIT - Interest + Non-Operating Income | C22: Profit Before Tax (PBT) | D22: =D18-D20+D21 -> 5933.07 | E22: =E18-E20+E21 -> 5202.02 | F22: =F18-F20+F21 -> 3799.63 | G22: =G18-G20+G21 -> 2202.51
B24: Tax Expense | C24: Current Tax | D24: 1120.54 | E24: 1040.08 | F24: 819.13 | G24: 521.42
C25: Deferred tax | D25: 78.09 | E25: 160.93 | F25: 66.56 | G25: 4.49
C26: Total Tax Expense | D26: =D24+D25 -> 1198.63 | E26: =E24+E25 -> 1201.01 | F26: =F24+F25 -> 885.69 | G26: =G24+G25 -> 525.91
B27: PBT - Tax | C27: Net Income or Proft After Tax (PAT) | D27: =D22-D26 -> 4734.44 | E27: =E22-E26 -> 4001.01 | F27: =F22-F26 -> 2913.94 | G27: =G22-G26 -> 1676.6

Sheet Eicher Motors BS
B3: Eicher Motors - Consolidated Balance Sheet ('INR Crore) | I3: Eicher Motors - Common Size Balance Sheet
C4: Consolidated Balance Sheet | D4: March 31, 2025 | E4: March 31, 2024 | F4: March 31, 2023 | G4: March 31, 2022 | J4: Consolidated Balance Sheet | K4: March 31, 2025 | L4: March 31, 2024 | M4: March 31, 2023 | N4: March 31, 2022
B6: ASSETS | I6: ASSETS
B8: Non-Current Assets | C8: Property, Plant and Equipment | D8: 2268.7 | E8: 1950.26 | F8: 1999.65 | G8: 1910.78 | I8: Non-Current Assets | J8: Property, Plant and Equipment | K8: ='Eicher Motors BS'!D8/'Eicher Motors BS'!D22 -> 0.083486633 | L8: ='Eicher Motors BS'!E8/'Eicher Motors BS'!E22 -> 0.084324883 | M8: ='Eicher Motors BS'!F8/'Eicher Motors BS'!F22 -> 0.10416124 | N8: ='Eicher Motors BS'!G8/'Eicher Motors BS'!G22 -> 0.1183891
C9: Intangible Assets (Goodwill) | D9: 887.73 | E9: 692.13 | F9: 464.21 | G9: 329.84 | J9: Intangible Assets (Goodwill) | K9: ='Eicher Motors BS'!D9/'Eicher Motors BS'!D22 -> 0.032667867 | L9: ='Eicher Motors BS'!E9/'Eicher Motors BS'!E22 -> 0.029926154 | M9: ='Eicher Motors BS'!F9/'Eicher Motors BS'!F22 -> 0.024180576 | N9: ='Eicher Motors BS'!G9/'Eicher Motors BS'!G22 -> 0.020436399
C10: Other Intangible Assets (Under Development) | D10: 381.17 | E10: 343.45 | F10: 394.32 | G10: 370.8 | J10: Other Intangible Assets (Under Development) | K10: ='Eicher Motors BS'!D10/'Eicher Motors BS'!D22 -> 0.014026799 | L10: ='Eicher Motors BS'!E10/'Eicher Motors BS'!E22 -> 0.01485001 | M10: ='Eicher Motors BS'!F10/'Eicher Motors BS'!F22 -> 0.020540025 | N10: ='Eicher Motors BS'!G10/'Eicher Motors BS'!G22 -> 0.02297422
C11: *Other Non-Current Assets | D11: 16682.65 | E11: 15990.76 | F11: 12656.23 | G11: 7909.07 | J11: *Other Non-Current Assets | K11: ='Eicher Motors BS'!D11/'Eicher Motors BS'!D22 -> 0.61391029 | L11: ='Eicher Motors BS'!E11/'Eicher Motors BS'!E22 -> 0.69140472 | M11: ='Eicher Motors BS'!F11/'Eicher Motors BS'!F22 -> 0.65925968 | N11: ='Eicher Motors BS'!G11/'Eicher Motors BS'!G22 -> 0.49003428
C12: Total Non-Current Assets | D12: =SUM(D8:D11) -> 20220.25 | E12: =SUM(E8:E11) -> 18976.6 | F12: =SUM(F8:F11) -> 15514.41 | G12: =SUM(G8:G11) -> 10520.49 | J12: Total Non-Current Assets | K12: ='Eicher Motors BS'!D12/'Eicher Motors BS'!D22 -> 0.74409159 | L12: ='Eicher Motors BS'!E12/'Eicher Motors BS'!E22 -> 0.82050577 | M12: ='Eicher Motors BS'!F12/'Eicher Motors BS'!F22 -> 0.80814152 | N12: ='Eicher Motors BS'!G12/'Eicher Motors BS'!G22 -> 0.651834
B14: Current Assets | C14: Inventories | D14: 1563.75 | E14: 1409.64 | F14: 1278.44 | G14: 1132.4 | I14: Current Assets | J14: Inventories | K14: ='Eicher Motors BS'!D14/'Eicher Motors BS'!D22 -> 0.057544948 | L14: ='Eicher Motors BS'!E14/'Eicher Motors BS'!E22 -> 0.060949683 | M14: ='Eicher Motors BS'!F14/'Eicher Motors BS'!F22 -> 0.066593602 | N14: ='Eicher Motors BS'!G14/'Eicher Motors BS'!G22 -> 0.070161829
C15: Trade Receivables (Billed and Unbilled) | D15: 549.64 | E15: 373.78 | F15: 368.92 | G15: 302.04 | J15: Trade Receivables (Billed and Unbilled) | K15: ='Eicher Motors BS'!D15/'Eicher Motors BS'!D22 -> 0.020226382 | L15: ='Eicher Motors BS'!E15/'Eicher Motors BS'!E22 -> 0.016161412 | M15: ='Eicher Motors BS'!F15/'Eicher Motors BS'!F22 -> 0.019216945 | N15: ='Eicher Motors BS'!G15/'Eicher Motors BS'!G22 -> 0.018713952
C16: Cash and Cash Equivalents | D16: 218.96 | E16: 107.21 | F16: 88.81 | G16: 50.53 | J16: Cash and Cash Equivalents | K16: ='Eicher Motors BS'!D16/'Eicher Motors BS'!D22 -> 0.0080575806 | L16: ='Eicher Motors BS'!E16/'Eicher Motors BS'!E22 -> 0.0046355208 | M16: ='Eicher Motors BS'!F16/'Eicher Motors BS'!F22 -> 0.0046260895 | N16: ='Eicher Motors BS'!G16/'Eicher Motors BS'!G22 -> 0.0031307641
C17: *Other Non-Current Assets | D17: 4621.81 | E17: 2260.7 | F17: 1947.06 | G17: 4134.37 | J17: *Other Non-Current Assets | K17: ='Eicher Motors BS'!D17/'Eicher Motors BS'!D22 -> 0.1700795 | L17: ='Eicher Motors BS'!E17/'Eicher Motors BS'!E22 -> 0.097747615 | M17: ='Eicher Motors BS'!F17/'Eicher Motors BS'!F22 -> 0.10142184 | N17: ='Eicher Motors BS'!G17/'Eicher Motors BS'!G22 -> 0.25615945
C18: Total Current Assets | D18: =SUM(D14:D17) -> 6954.16 | E18: =SUM(E14:E17) -> 4151.33 | F18: =SUM(F14:F17) -> 3683.23 | G18: =SUM(G14:G17) -> 5619.34 | J18: Total Current Assets | K18: ='Eicher Motors BS'!D18/'Eicher Motors BS'!D22 -> 0.25590841 | L18: ='Eicher Motors BS'!E18/'Eicher Motors BS'!E22 -> 0.17949423 | M18: ='Eicher Motors BS'!F18/'Eicher Motors BS'!F22 -> 0.19185848 | N18: ='Eicher Motors BS'!G18/'Eicher Motors BS'!G22 -> 0.348166
B20: Total Assets | D20: =D12+D18 -> 27174.41 | E20: =E12+E18 -> 23127.93 | F20: =F12+F18 -> 19197.64 | G20: =G12+G18 -> 16139.83 | I20: Total Assets | K20: ='Eicher Motors BS'!D20/'Eicher Motors BS'!D20 -> 1 | L20: ='Eicher Motors BS'!E20/'Eicher Motors BS'!E20 -> 1 | M20: ='Eicher Motors BS'!F20/'Eicher Motors BS'!F20 -> 1 | N20: ='Eicher Motors BS'!G20/'Eicher Motors BS'!G20 -> 1
B22: Total Assets | D22: =D12+D18 -> 27174.41 | E22: =E12+E18 -> 23127.93 | F22: =F12+F18 -> 19197.64 | G22: =G12+G18 -> 16139.83 | I22: Total Assets | K22: ='Eicher Motors BS'!D22/'Eicher Motors BS'!D22 -> 1 | L22: ='Eicher Motors BS'!E22/'Eicher Motors BS'!E22 -> 1 | M22: ='Eicher Motors BS'!F22/'Eicher Motors BS'!F22 -> 1 | N22: ='Eicher Motors BS'!G22/'Eicher Motors BS'!G22 -> 1
B24: EQUITY & LIABILITY | I24: EQUITY & LIABILITY
B26: Equity | C26: Share Capital | D26: 27.42 | E26: 27.38 | F26: 27.35 | G26: 27.34 | I26: Equity | J26: Share Capital | K26: ='Eicher Motors BS'!D26/'Eicher Motors BS'!D42 -> 0.0010090375 | L26: ='Eicher Motors BS'!E26/'Eicher Motors BS'!E42 -> 0.00118385 | M26: ='Eicher Motors BS'!F26/'Eicher Motors BS'!F42 -> 0.0014246543 | N26: ='Eicher Motors BS'!G26/'Eicher Motors BS'!G42 -> 0.001693946
C27: Other equity | D27: 21269.07 | E27: 18018.15 | F27: 14962.93 | G27: 12580.66 | J27: Other equity | K27: ='Eicher Motors BS'!D27/'Eicher Motors BS'!D42 -> 0.78268746 | L27: ='Eicher Motors BS'!E27/'Eicher Motors BS'!E42 -> 0.77906453 | M27: ='Eicher Motors BS'!F27/'Eicher Motors BS'!F42 -> 0.77941507 | N27: ='Eicher Motors BS'!G27/'Eicher Motors BS'!G42 -> 0.77947909
C28: Total Equity | D28: =SUM(D26:D27) -> 21296.49 | E28: =SUM(E26:E27) -> 18045.53 | F28: =SUM(F26:F27) -> 14990.28 | G28: =SUM(G26:G27) -> 12608 | J28: Total Equity | K28: ='Eicher Motors BS'!D28/'Eicher Motors BS'!D42 -> 0.7836965 | L28: ='Eicher Motors BS'!E28/'Eicher Motors BS'!E42 -> 0.78024838 | M28: ='Eicher Motors BS'!F28/'Eicher Motors BS'!F42 -> 0.78083973 | N28: ='Eicher Motors BS'!G28/'Eicher Motors BS'!G42 -> 0.78117304
B30: Total Equity | D30: =D26+D27 -> 21296.49 | E30: =E26+E27 -> 18045.53 | F30: =F26+F27 -> 14990.28 | G30: =G26+G27 -> 12608 | I30: Total Equity | K30: ='Eicher Motors BS'!D30/'Eicher Motors BS'!D42 -> 0.7836965 | L30: ='Eicher Motors BS'!E30/'Eicher Motors BS'!E42 -> 0.78024838 | M30: ='Eicher Motors BS'!F30/'Eicher Motors BS'!F42 -> 0.78083973 | N30: ='Eicher Motors BS'!G30/'Eicher Motors BS'!G42 -> 0.78117304
B32: Non-Current Liabilities | C32: Provisions | D32: 194.91 | E32: 175.02 | F32: 102.46 | G32: 67.96 | I32: Non-Current Liabilities | J32: Provisions | K32: ='Eicher Motors BS'!D32/'Eicher Motors BS'!D42 -> 0.0071725568 | L32: ='Eicher Motors BS'!E32/'Eicher Motors BS'!E42 -> 0.0075674736 | M32: ='Eicher Motors BS'!F32/'Eicher Motors BS'!F42 -> 0.0053371144 | N32: ='Eicher Motors BS'!G32/'Eicher Motors BS'!G42 -> 0.0042107011
C33: *Other Non-Current Liabilities | D33: 1417.23 | E33: 1308.97 | F33: 870.32 | G33: 570.5 | J33: *Other Non-Current Liabilities | K33: ='Eicher Motors BS'!D33/'Eicher Motors BS'!D42 -> 0.05215311 | L33: ='Eicher Motors BS'!E33/'Eicher Motors BS'!E42 -> 0.056596937 | M33: ='Eicher Motors BS'!F33/'Eicher Motors BS'!F42 -> 0.045334739 | N33: ='Eicher Motors BS'!G33/'Eicher Motors BS'!G42 -> 0.035347336
C34: Total Non-Current Liabilities | D34: =D32+D33 -> 1612.14 | E34: =E32+E33 -> 1483.99 | F34: =F32+F33 -> 972.78 | G34: =G32+G33 -> 638.46 | J34: Total Non-Current Liabilities | K34: ='Eicher Motors BS'!D34/'Eicher Motors BS'!D42 -> 0.059325667 | L34: ='Eicher Motors BS'!E34/'Eicher Motors BS'!E42 -> 0.064164411 | M34: ='Eicher Motors BS'!F34/'Eicher Motors BS'!F42 -> 0.050671853 | N34: ='Eicher Motors BS'!G34/'Eicher Motors BS'!G42 -> 0.039558037
B36: Current Liabilities | C36: Trade payables | D36: 2529.75 | E36: 2090.13 | F36: 1810.44 | G36: 1788.09 | I36: Current Liabilities | J36: Trade payables | K36: ='Eicher Motors BS'!D36/'Eicher Motors BS'!D42 -> 0.093093098 | L36: ='Eicher Motors BS'!E36/'Eicher Motors BS'!E42 -> 0.09037255 | M36: ='Eicher Motors BS'!F36/'Eicher Motors BS'!F42 -> 0.094305342 | N36: ='Eicher Motors BS'!G36/'Eicher Motors BS'!G42 -> 0.11078741
C37: *Other Current Liabilities | D37: 1736.03 | E37: 1508.28 | F37: 1424.14 | G37: 1105.28 | J37: *Other Current Liabilities | K37: ='Eicher Motors BS'!D37/'Eicher Motors BS'!D42 -> 0.063884736 | L37: ='Eicher Motors BS'!E37/'Eicher Motors BS'!E42 -> 0.065214656 | M37: ='Eicher Motors BS'!F37/'Eicher Motors BS'!F42 -> 0.074183077 | N37: ='Eicher Motors BS'!G37/'Eicher Motors BS'!G42 -> 0.068481514
C38: Total Current Liabilities | D38: =D36+D37 -> 4265.78 | E38: =E36+E37 -> 3598.41 | F38: =F36+F37 -> 3234.58 | G38: =G36+G37 -> 2893.37 | J38: Total Current Liabilities | K38: ='Eicher Motors BS'!D38/'Eicher Motors BS'!D42 -> 0.15697783 | L38: ='Eicher Motors BS'!E38/'Eicher Motors BS'!E42 -> 0.15558721 | M38: ='Eicher Motors BS'!F38/'Eicher Motors BS'!F42 -> 0.16848842 | N38: ='Eicher Motors BS'!G38/'Eicher Motors BS'!G42 -> 0.17926893
B40: Total Liability | D40: =D34+D38 -> 5877.92 | E40: =E34+E38 -> 5082.4 | F40: =F34+F38 -> 4207.36 | G40: =G34+G38 -> 3531.83 | I40: Total Liability | K40: ='Eicher Motors BS'!D40/'Eicher Motors BS'!D42 -> 0.2163035 | L40: ='Eicher Motors BS'!E40/'Eicher Motors BS'!E42 -> 0.21975162 | M40: ='Eicher Motors BS'!F40/'Eicher Motors BS'!F42 -> 0.21916027 | N40: ='Eicher Motors BS'!G40/'Eicher Motors BS'!G42 -> 0.21882696
B42: Total Equity and Liability | D42: =D30+D40 -> 27174.41 | E42: =E30+E40 -> 23127.93 | F42: =F30+F40 -> 19197.64 | G42: =G30+G40 -> 16139.83 | I42: Total Equity and Liability | K42: ='Eicher Motors BS'!D42/'Eicher Motors BS'!D42 -> 1 | L42: ='Eicher Motors BS'!E42/'Eicher Motors BS'!E42 -> 1 | M42: ='Eicher Motors BS'!F42/'Eicher Motors BS'!F42 -> 1 | N42: ='Eicher Motors BS'!G42/'Eicher Motors BS'!G42 -> 1

Sheet SML Isuzu IS
B3: SML Isuzu - Consolidated Income Statement ('INR Crore) | I3: SML Isuzu - Common Size Income Statement
C4: Consolidated Income Statement | D4: March 31, 2025 | E4: March 31, 2024 | F4: March 31, 2023 | G4: March 31, 2022 | I4: Consolidated Income Statement | J4: March 31, 2025 | K4: March 31, 2024 | L4: March 31, 2023 | M4: March 31, 2022
B5: Revenue or Sales | C5: Revenue from Operations | D5: 239899.28 | E5: 219593.38 | F5: 182159.09 | G5: 92416.98 | I5: Total Revenue or Income | J5: 240504.62 | K5: 220133.92 | L5: 182470.61 | M5: 93013.34
C6: Other Income | D6: 605.34 | E6: 540.54 | F6: 311.52 | G6: 596.36 | I6: Cost of Materials Consumed | J6: ='SML Isuzu IS'!D8/J5 -> 0.71785873 | K6: ='SML Isuzu IS'!E8/K5 -> 0.7971533 | L6: ='SML Isuzu IS'!F8/L5 -> 0.81757424 | M6: ='SML Isuzu IS'!G8/M5 -> 0.77835695
C7: Total Revenue or Income | D7: =D5+D6 -> 240504.62 | E7: =E5+E6 -> 220133.92 | F7: =F5+F6 -> 182470.61 | G7: =G5+G6 -> 93013.34 | I7: Purchase of Stock-in-Trade | J7: ='SML Isuzu IS'!D9/J5 -> 0.036526991 | K7: ='SML Isuzu IS'!E9/K5 -> 0.035618454 | L7: ='SML Isuzu IS'!F9/L5 -> 0.043009447 | M7: ='SML Isuzu IS'!G9/M5 -> 0.058482041
B8: Cost Of Goods Sold (COGS) | C8: Cost of Materials Consumed | D8: 172648.34 | E8: 175480.48 | F8: 149183.27 | G8: 72397.58 | I8: Total COGS | J8: ='SML Isuzu IS'!D11/J5 -> 0.75762374 | K8: ='SML Isuzu IS'!E11/K5 -> 0.77104296 | L8: ='SML Isuzu IS'!F11/L5 -> 0.80078315 | M8: ='SML Isuzu IS'!G11/M5 -> 0.81434652
C9: Purchase of Stock-in-Trade | D9: 8784.91 | E9: 7840.83 | F9: 7847.96 | G9: 5439.61 | I9: Gross Profit | J9: ='SML Isuzu IS'!D12/J5 -> 0.24237626 | K9: ='SML Isuzu IS'!E12/K5 -> 0.22895704 | L9: ='SML Isuzu IS'!F12/L5 -> 0.19921685 | M9: ='SML Isuzu IS'!G12/M5 -> 0.18565348
C10: Changes in Inventories of Finished Foods, Work in Progress and Stock-in-Trade | D10: 778.76 | E10: -13588.6 | F10: -10911.84 | G10: -2092.1 | I10: Employee Benefits Expense | J10: ='SML Isuzu IS'!D14/J5 -> 0.085761513 | K10: ='SML Isuzu IS'!E14/K5 -> 0.088896386 | L10: ='SML Isuzu IS'!F14/L5 -> 0.094509412 | M10: ='SML Isuzu IS'!G14/M5 -> 0.14275468
C11: Total COGS | D11: =SUM(D8:D10) -> 182212.01 | E11: =SUM(E8:E10) -> 169732.71 | F11: =SUM(F8:F10) -> 146119.39 | G11: =SUM(G8:G10) -> 75745.09 | I11: Depreciation and Amortisation Expense | J11: ='SML Isuzu IS'!D15/J5 -> 0.020104853 | K11: ='SML Isuzu IS'!E15/K5 -> 0.02158527 | L11: ='SML Isuzu IS'!F15/L5 -> 0.023254046 | M11: ='SML Isuzu IS'!G15/M5 -> 0.046795223
B12: Revenue - COGS | C12: Gross Profit | D12: =D7-D11 -> 58292.61 | E12: =E7-E11 -> 50401.21 | F12: =F7-F11 -> 36351.22 | G12: =G7-G11 -> 17268.25 | I12: Other Expenses | J12: ='SML Isuzu IS'!D16/J5 -> 0.056571387 | K12: ='SML Isuzu IS'!E16/K5 -> 0.056331437 | L12: ='SML Isuzu IS'!F16/L5 -> 0.05826078 | M12: ='SML Isuzu IS'!G16/M5 -> 0.080771962
I13: Total OPEX | J13: ='SML Isuzu IS'!D17/J5 -> 0.16243775 | K13: ='SML Isuzu IS'!E17/K5 -> 0.16681309 | L13: ='SML Isuzu IS'!F17/L5 -> 0.17602424 | M13: ='SML Isuzu IS'!G17/M5 -> 0.27032187
B14: Operating Expenses (OPEX) | C14: Employee Benefits Expense | D14: 20626.04 | E14: 19569.11 | F14: 17245.19 | G14: 13278.09 | I14: Operating Profit or Earnings Before Interest and Taxes (EBIT) | J14: ='SML Isuzu IS'!D18/J5 -> 0.079938506 | K14: ='SML Isuzu IS'!E18/K5 -> 0.062143944 | L14: ='SML Isuzu IS'!F18/L5 -> 0.023192612 | M14: ='SML Isuzu IS'!G18/M5 -> -0.084668393
C15: Depreciation and Amortisation Expense | D15: 4835.31 | E15: 4751.65 | F15: 4243.18 | G15: 4352.58 | I15: Finance Costs | J15: ='SML Isuzu IS'!D20/J5 -> 0.012423462 | K15: ='SML Isuzu IS'!E20/K5 -> 0.013786653 | L15: ='SML Isuzu IS'!F20/L5 -> 0.013725005 | M15: ='SML Isuzu IS'!G20/M5 -> 0.02312937
C16: Other Expenses | D16: 13605.68 | E16: 12400.46 | F16: 10630.88 | G16: 7512.87 | I16: Profit Before Tax (PBT) | J16: ='SML Isuzu IS'!D21/J5 -> 0.067515044 | K16: ='SML Isuzu IS'!E21/K5 -> 0.048357291 | L16: ='SML Isuzu IS'!F21/L5 -> 0.0094676069 | M16: ='SML Isuzu IS'!G21/M5 -> -0.10779776
C17: Total OPEX | D17: =SUM(D14:D16) -> 39067.03 | E17: =SUM(E14:E16) -> 36721.22 | F17: =SUM(F14:F16) -> 32119.25 | G17: =SUM(G14:G16) -> 25143.54 | I17: Current Tax | J17: ='SML Isuzu IS'!D23/J5 -> 0.0015056675 | K17: --% | L17: --% | M17: --%
B18: Gross Profit - OPEX | C18: Operating Profit or Earnings Before Interest and Taxes (EBIT) | D18: =D12-D17 -> 19225.58 | E18: =E12-E17 -> 13679.99 | F18: =F12-F17 -> 4231.97 | G18: =G12-G17 -> -7875.29 | I18: Tax Adjustment Related to Prior Years | J18: ='SML Isuzu IS'!D24/J5 -> -0.00012935302 | K18: ='SML Isuzu IS'!E24/K5 -> 3.5114988e-05 | L18: ='SML Isuzu IS'!F24/L5 -> -0.00013059637 | M18: ='SML Isuzu IS'!G24/M5 -> -0.00054379297
I19: Deferred tax | J19: ='SML Isuzu IS'!D25/J5 -> 0.015547435 | K19: ='SML Isuzu IS'!E25/K5 -> -0.0006834476 | L19: ='SML Isuzu IS'!F25/L5 -> -0.0012721501 | M19: --%
B20: Interest | C20: Finance Costs | D20: 2987.9 | E20: 3034.91 | F20: 2504.41 | G20: 2151.34 | I20: Total Tax Expense | J20: ='SML Isuzu IS'!D26/J5 -> 0.01692375 | K20: ='SML Isuzu IS'!E26/K5 -> -0.00064833261 | L20: ='SML Isuzu IS'!F26/L5 -> -0.0014027464 | M20: ='SML Isuzu IS'!G26/M5 -> -0.00054379297
B21: EBIT - Interest | C21: Profit Before Tax (PBT) | D21: =D18-D20 -> 16237.68 | E21: =E18-E20 -> 10645.08 | F21: =F18-F20 -> 1727.56 | G21: =G18-G20 -> -10026.63 | I21: Net Income or Proft After Tax (PAT) | J21: ='SML Isuzu IS'!D27/J5 -> 0.050591294 | K21: ='SML Isuzu IS'!E27/K5 -> 0.049005623 | L21: ='SML Isuzu IS'!F27/L5 -> 0.010870353 | M21: ='SML Isuzu IS'!G27/M5 -> -0.10725397
B23: Tax Expense | C23: Current Tax | D23: 362.12 | E23: -- | F23: -- | G23: --
C24: Tax Adjustment Related to Prior Years | D24: -31.11 | E24: 7.73 | F24: -23.83 | G24: -50.58
C25: Deferred tax | D25: 3739.23 | E25: -150.45 | F25: -232.13 | G25: --
C26: Total Tax Expense | D26: =SUM(D23:D25) -> 4070.24 | E26: =SUM(E23:E25) -> -142.72 | F26: =SUM(F23:F25) -> -255.96 | G26: =SUM(G23:G25) -> -50.58
B27: PBT - Tax | C27: Net Income or Proft After Tax (PAT) | D27: =D21-D26 -> 12167.44 | E27: =E21-E26 -> 10787.8 | F27: =F21-F26 -> 1983.52 | G27: =G21-G26 -> -9976.05

Sheet SML Isuzu BS
B3: SML Isuzu - Consolidated Balance Sheet ('INR Crore) | I3: SML Isuzu - Common Size Balance Sheet
C4: Consolidated Balance Sheet | D4: March 31, 2025 | E4: March 31, 2024 | F4: March 31, 2023 | G4: March 31, 2022 | J4: Consolidated Balance Sheet | K4: March 31, 2025 | L4: March 31, 2024 | M4: March 31, 2023 | N4: March 31, 2022
B6: ASSETS | I6: ASSETS
B8: Non-Current Assets | C8: Property, Plant and Equipment | D8: 26344.63 | E8: 26719.4 | F8: 27531.1 | G8: 29343.34 | I8: Non-Current Assets | J8: Property, Plant and Equipment | K8: ='SML Isuzu BS'!D8/'SML Isuzu BS'!D22 -> 0.20274258 | L8: ='SML Isuzu BS'!E8/'SML Isuzu BS'!E22 -> 0.22036235 | M8: ='SML Isuzu BS'!F8/'SML Isuzu BS'!F22 -> 0.29395859 | N8: ='SML Isuzu BS'!G8/'SML Isuzu BS'!G22 -> 0.3596768
C9: Intangible Assets (Goodwill) | D9: 5302.73 | E9: 6830.17 | F9: 7465.35 | G9: 4944.74 | J9: Intangible Assets (Goodwill) | K9: ='SML Isuzu BS'!D9/'SML Isuzu BS'!D22 -> 0.040808664 | L9: ='SML Isuzu BS'!E9/'SML Isuzu BS'!E22 -> 0.056330319 | M9: ='SML Isuzu BS'!F9/'SML Isuzu BS'!F22 -> 0.079709991 | N9: ='SML Isuzu BS'!G9/'SML Isuzu BS'!G22 -> 0.060610288
C10: Other Intangible Assets (Under Development) | D10: 1720.24 | E10: 800.79 | F10: 1024.5 | G10: 1165.82 | J10: Other Intangible Assets (Under Development) | K10: ='SML Isuzu BS'!D10/'SML Isuzu BS'!D22 -> 0.013238595 | L10: ='SML Isuzu BS'!E10/'SML Isuzu BS'!E22 -> 0.0066043387 | M10: ='SML Isuzu BS'!F10/'SML Isuzu BS'!F22 -> 0.010938923 | N10: ='SML Isuzu BS'!G10/'SML Isuzu BS'!G22 -> 0.014290071
C11: *Other Non-Current Assets | D11: 6244.37 | E11: 4441 | F11: 3819.02 | G11: 4079.99 | J11: *Other Non-Current Assets | K11: ='SML Isuzu BS'!D11/'SML Isuzu BS'!D22 -> 0.048055322 | L11: ='SML Isuzu BS'!E11/'SML Isuzu BS'!E22 -> 0.036626167 | M11: ='SML Isuzu BS'!F11/'SML Isuzu BS'!F22 -> 0.040776929 | N11: ='SML Isuzu BS'!G11/'SML Isuzu BS'!G22 -> 0.050010591
C12: Total Non-Current Assets | D12: =SUM(D8:D11) -> 39611.97 | E12: =SUM(E8:E11) -> 38791.36 | F12: =SUM(F8:F11) -> 39839.97 | G12: =SUM(G8:G11) -> 39533.89 | J12: Total Non-Current Assets | K12: ='SML Isuzu BS'!D12/'SML Isuzu BS'!D22 -> 0.30484516 | L12: ='SML Isuzu BS'!E12/'SML Isuzu BS'!E22 -> 0.31992317 | M12: ='SML Isuzu BS'!F12/'SML Isuzu BS'!F22 -> 0.42538443 | N12: ='SML Isuzu BS'!G12/'SML Isuzu BS'!G22 -> 0.48458775
B14: Current Assets | C14: Inventories | D14: 57799.37 | E14: 57973.06 | F14: 42189.29 | G14: 29599.21 | I14: Current Assets | J14: Inventories | K14: ='SML Isuzu BS'!D14/'SML Isuzu BS'!D22 -> 0.44481146 | L14: ='SML Isuzu BS'!E14/'SML Isuzu BS'!E22 -> 0.47812001 | M14: ='SML Isuzu BS'!F14/'SML Isuzu BS'!F22 -> 0.45046889 | N14: ='SML Isuzu BS'!G14/'SML Isuzu BS'!G22 -> 0.36281314
C15: Trade Receivables (Billed and Unbilled) | D15: 26525.31 | E15: 16897.23 | F15: 7574.73 | G15: 7891.82 | J15: Trade Receivables (Billed and Unbilled) | K15: ='SML Isuzu BS'!D15/'SML Isuzu BS'!D22 -> 0.20413305 | L15: ='SML Isuzu BS'!E15/'SML Isuzu BS'!E22 -> 0.13935617 | M15: ='SML Isuzu BS'!F15/'SML Isuzu BS'!F22 -> 0.080877877 | N15: ='SML Isuzu BS'!G15/'SML Isuzu BS'!G22 -> 0.096734202
C16: Cash and Cash Equivalents | D16: 310.1 | E16: 3482.01 | F16: 349.16 | G16: 1067.33 | J16: Cash and Cash Equivalents | K16: ='SML Isuzu BS'!D16/'SML Isuzu BS'!D22 -> 0.0023864626 | L16: ='SML Isuzu BS'!E16/'SML Isuzu BS'!E22 -> 0.028717109 | M16: ='SML Isuzu BS'!F16/'SML Isuzu BS'!F22 -> 0.0037280959 | N16: ='SML Isuzu BS'!G16/'SML Isuzu BS'!G22 -> 0.013082827
C17: *Other Non-Current Assets | D17: 5694.53 | E17: 4108.45 | F17: 3703.24 | G17: 3490.27 | J17: *Other Non-Current Assets | K17: ='SML Isuzu BS'!D17/'SML Isuzu BS'!D22 -> 0.043823872 | L17: ='SML Isuzu BS'!E17/'SML Isuzu BS'!E22 -> 0.033883534 | M17: ='SML Isuzu BS'!F17/'SML Isuzu BS'!F22 -> 0.039540708 | N17: ='SML Isuzu BS'!G17/'SML Isuzu BS'!G22 -> 0.042782081
C18: Total Current Assets | D18: =SUM(D14:D17) -> 90329.31 | E18: =SUM(E14:E17) -> 82460.75 | F18: =SUM(F14:F17) -> 53816.42 | G18: =SUM(G14:G17) -> 42048.63 | J18: Total Current Assets | K18: ='SML Isuzu BS'!D18/'SML Isuzu BS'!D22 -> 0.69515484 | L18: ='SML Isuzu BS'!E18/'SML Isuzu BS'!E22 -> 0.68007683 | M18: ='SML Isuzu BS'!F18/'SML Isuzu BS'!F22 -> 0.57461557 | N18: ='SML Isuzu BS'!G18/'SML Isuzu BS'!G22 -> 0.51541225
B20: Total Assets | D20: =D12+D18 -> 129941.28 | E20: =E12+E18 -> 121252.11 | F20: =F12+F18 -> 93656.39 | G20: =G12+G18 -> 81582.52 | I20: Total Assets | K20: ='SML Isuzu BS'!D20/'SML Isuzu BS'!D20 -> 1 | L20: ='SML Isuzu BS'!E20/'SML Isuzu BS'!E20 -> 1 | M20: ='SML Isuzu BS'!F20/'SML Isuzu BS'!F20 -> 1 | N20: ='SML Isuzu BS'!G20/'SML Isuzu BS'!G20 -> 1
B22: Total Assets | D22: =D12+D18 -> 129941.28 | E22: =E12+E18 -> 121252.11 | F22: =F12+F18 -> 93656.39 | G22: =G12+G18 -> 81582.52 | I22: Total Assets | K22: ='SML Isuzu BS'!D22/'SML Isuzu BS'!D22 -> 1 | L22: ='SML Isuzu BS'!E22/'SML Isuzu BS'!E22 -> 1 | M22: ='SML Isuzu BS'!F22/'SML Isuzu BS'!F22 -> 1 | N22: ='SML Isuzu BS'!G22/'SML Isuzu BS'!G22 -> 1
B24: EQUITY & LIABILITY | I24: EQUITY & LIABILITY
B26: Equity | C26: Share Capital | D26: 1447.88 | E26: 1447.88 | F26: 1447.88 | G26: 1447.88 | I26: Equity | J26: Share Capital | K26: ='SML Isuzu BS'!D26/'SML Isuzu BS'!D42 -> 0.011142571 | L26: ='SML Isuzu BS'!E26/'SML Isuzu BS'!E42 -> 0.011941071 | M26: ='SML Isuzu BS'!F26/'SML Isuzu BS'!F42 -> 0.01545949 | N26: ='SML Isuzu BS'!G26/'SML Isuzu BS'!G42 -> 0.017747429
C27: Other equity | D27: 36818.39 | E27: 27111 | F27: 16346.79 | G27: 14700.62 | J27: Other equity | K27: ='SML Isuzu BS'!D27/'SML Isuzu BS'!D42 -> 0.28334637 | L27: ='SML Isuzu BS'!E27/'SML Isuzu BS'!E42 -> 0.22359199 | M27: ='SML Isuzu BS'!F27/'SML Isuzu BS'!F42 -> 0.17454004 | N27: ='SML Isuzu BS'!G27/'SML Isuzu BS'!G42 -> 0.18019326
C28: Total Equity | D28: =D26+D27 -> 38266.27 | E28: =E26+E27 -> 28558.88 | F28: =F26+F27 -> 17794.67 | G28: =G26+G27 -> 16148.5 | J28: Total Equity | K28: ='SML Isuzu BS'!D28/'SML Isuzu BS'!D42 -> 0.29448894 | L28: ='SML Isuzu BS'!E28/'SML Isuzu BS'!E42 -> 0.23553306 | M28: ='SML Isuzu BS'!F28/'SML Isuzu BS'!F42 -> 0.18999953 | N28: ='SML Isuzu BS'!G28/'SML Isuzu BS'!G42 -> 0.19794069
B30: Total Equity | D30: =D26+D27 -> 38266.27 | E30: =E26+E27 -> 28558.88 | F30: =F26+F27 -> 17794.67 | G30: =G26+G27 -> 16148.5 | I30: Total Equity | K30: ='SML Isuzu BS'!D30/'SML Isuzu BS'!D42 -> 0.29448894 | L30: ='SML Isuzu BS'!E30/'SML Isuzu BS'!E42 -> 0.23553306 | M30: ='SML Isuzu BS'!F30/'SML Isuzu BS'!F42 -> 0.18999953 | N30: ='SML Isuzu BS'!G30/'SML Isuzu BS'!G42 -> 0.19794069
B32: Non-Current Liabilities | C32: Provisions | D32: 4800.74 | E32: 5027.71 | F32: 4007.25 | G32: 3442.49 | I32: Non-Current Liabilities | J32: Provisions | K32: ='SML Isuzu BS'!D32/'SML Isuzu BS'!D42 -> 0.036945457 | L32: ='SML Isuzu BS'!E32/'SML Isuzu BS'!E42 -> 0.041464928 | M32: ='SML Isuzu BS'!F32/'SML Isuzu BS'!F42 -> 0.042786723 | N32: ='SML Isuzu BS'!G32/'SML Isuzu BS'!G42 -> 0.042196417
C33: *Other Non-Current Liabilities | D33: 9704.19 | E33: 5709.96 | F33: 3358.3 | G33: 2652.95 | J33: *Other Non-Current Liabilities | K33: ='SML Isuzu BS'!D33/'SML Isuzu BS'!D42 -> 0.074681348 | L33: ='SML Isuzu BS'!E33/'SML Isuzu BS'!E42 -> 0.047091634 | M33: ='SML Isuzu BS'!F33/'SML Isuzu BS'!F42 -> 0.035857671 | N33: ='SML Isuzu BS'!G33/'SML Isuzu BS'!G42 -> 0.032518608
C34: Total Non-Current Liabilities | D34: =D32+D33 -> 14504.93 | E34: =E32+E33 -> 10737.67 | F34: =F32+F33 -> 7365.55 | G34: =G32+G33 -> 6095.44 | J34: Total Non-Current Liabilities | K34: ='SML Isuzu BS'!D34/'SML Isuzu BS'!D42 -> 0.11162681 | L34: ='SML Isuzu BS'!E34/'SML Isuzu BS'!E42 -> 0.088556562 | M34: ='SML Isuzu BS'!F34/'SML Isuzu BS'!F42 -> 0.078644394 | N34: ='SML Isuzu BS'!G34/'SML Isuzu BS'!G42 -> 0.074715025
B36: Current Liabilities | C36: Trade payables | D36: 37012.7 | E36: 33187.75 | F36: 29160.52 | G36: 24474.8 | I36: Current Liabilities | J36: Trade payables | K36: ='SML Isuzu BS'!D36/'SML Isuzu BS'!D42 -> 0.28484174 | L36: ='SML Isuzu BS'!E36/'SML Isuzu BS'!E42 -> 0.27370864 | M36: ='SML Isuzu BS'!F36/'SML Isuzu BS'!F42 -> 0.31135644 | N36: ='SML Isuzu BS'!G36/'SML Isuzu BS'!G42 -> 0.30000054
C37: *Other Current Liabilities | D37: 40157.38 | E37: 48767.81 | F37: 39335.65 | G37: 34863.78 | J37: *Other Current Liabilities | K37: ='SML Isuzu BS'!D37/'SML Isuzu BS'!D42 -> 0.30904252 | L37: ='SML Isuzu BS'!E37/'SML Isuzu BS'!E42 -> 0.40220174 | M37: ='SML Isuzu BS'!F37/'SML Isuzu BS'!F42 -> 0.41999964 | N37: ='SML Isuzu BS'!G37/'SML Isuzu BS'!G42 -> 0.42734375
C38: Total Current Liabilities | D38: =D36+D37 -> 77170.08 | E38: =E36+E37 -> 81955.56 | F38: =F36+F37 -> 68496.17 | G38: =G36+G37 -> 59338.58 | J38: Total Current Liabilities | K38: ='SML Isuzu BS'!D38/'SML Isuzu BS'!D42 -> 0.59388425 | L38: ='SML Isuzu BS'!E38/'SML Isuzu BS'!E42 -> 0.67591038 | M38: ='SML Isuzu BS'!F38/'SML Isuzu BS'!F42 -> 0.73135608 | N38: ='SML Isuzu BS'!G38/'SML Isuzu BS'!G42 -> 0.72734429
B40: Total Liability | D40: =D34+D38 -> 91675.01 | E40: =E34+E38 -> 92693.23 | F40: =F34+F38 -> 75861.72 | G40: =G34+G38 -> 65434.02 | I40: Total Liability | K40: ='SML Isuzu BS'!D40/'SML Isuzu BS'!D42 -> 0.70551106 | L40: ='SML Isuzu BS'!E40/'SML Isuzu BS'!E42 -> 0.76446694 | M40: ='SML Isuzu BS'!F40/'SML Isuzu BS'!F42 -> 0.81000047 | N40: ='SML Isuzu BS'!G40/'SML Isuzu BS'!G42 -> 0.80205931
B42: Total Equity and Liability | D42: =D30+D40 -> 129941.28 | E42: =E30+E40 -> 121252.11 | F42: =F30+F40 -> 93656.39 | G42: =G30+G40 -> 81582.52 | I42: Total Equity and Liability | K42: ='SML Isuzu BS'!D42/'SML Isuzu BS'!D42 -> 1 | L42: ='SML Isuzu BS'!E42/'SML Isuzu BS'!E42 -> 1 | M42: ='SML Isuzu BS'!F42/'SML Isuzu BS'!F42 -> 1 | N42: ='SML Isuzu BS'!G42/'SML Isuzu BS'!G42 -> 1

Sheet Liquidity Ratio
B3: Current Ratio
B4: Company Name | C4: March 31, 2025 | D4: March 31, 2024 | E4: March 31, 2023 | F4: March 31, 2022
B5: Eicher Motors | C5: ='Eicher Motors BS'!D18/'Eicher Motors BS'!D38 -> 1.63022 | D5: ='Eicher Motors BS'!E18/'Eicher Motors BS'!E38 -> 1.1536568 | E5: ='Eicher Motors BS'!F18/'Eicher Motors BS'!F38 -> 1.1387043 | F5: ='Eicher Motors BS'!G18/'Eicher Motors BS'!G38 -> 1.9421436
B6: SML Isuzu | C6: ='SML Isuzu BS'!D18/'SML Isuzu BS'!D38 -> 1.1705224 | D6: ='SML Isuzu BS'!E18/'SML Isuzu BS'!E38 -> 1.0061642 | E6: ='SML Isuzu BS'!F18/'SML Isuzu BS'!F38 -> 0.7856851 | F6: ='SML Isuzu BS'!G18/'SML Isuzu BS'!G38 -> 0.70862211
B7: Baseline | C7: 1 | D7: 1 | E7: 1 | F7: 1
B10: Acid-Test (Quick) Ratio
B11: Company Name | C11: March 31, 2025 | D11: March 31, 2024 | E11: March 31, 2023 | F11: March 31, 2022
B12: Eicher Motors | C12: =sum('Eicher Motors BS'!D15:D16)/('Eicher Motors BS'!D38) -> 0.18017807 | D12: =sum('Eicher Motors BS'!E15:E16)/('Eicher Motors BS'!E38) -> 0.13366737 | E12: =sum('Eicher Motors BS'!F15:F16)/('Eicher Motors BS'!F38) -> 0.14151142 | F12: =sum('Eicher Motors BS'!G15:G16)/('Eicher Motors BS'!G38) -> 0.12185445
B13: SML Isuzu | C13: =sum('SML Isuzu BS'!D15:D16)/'SML Isuzu BS'!D38 -> 0.34774371 | D13: =sum('SML Isuzu BS'!E15:E16)/'SML Isuzu BS'!E38 -> 0.24866208 | E13: =sum('SML Isuzu BS'!F15:F16)/'SML Isuzu BS'!F38 -> 0.11568369 | F13: =sum('SML Isuzu BS'!G15:G16)/'SML Isuzu BS'!G38 -> 0.15098356
B14: Baseline | C14: 1 | D14: 1 | E14: 1 | F14: 1
B17: Cash Ratio
B18: Company Name | C18: March 31, 2025 | D18: March 31, 2024 | E18: March 31, 2023 | F18: March 31, 2022
B19: Eicher Motors | C19: ='Eicher Motors BS'!D16/'Eicher Motors BS'!D38 -> 0.051329417 | D19: ='Eicher Motors BS'!E16/'Eicher Motors BS'!E38 -> 0.029793714 | E19: ='Eicher Motors BS'!F16/'Eicher Motors BS'!F38 -> 0.027456424 | F19: ='Eicher Motors BS'!G16/'Eicher Motors BS'!G38 -> 0.017464064
B20: SML Isuzu | C20: ='SML Isuzu BS'!D16/'SML Isuzu BS'!D38 -> 0.0040183968 | D20: ='SML Isuzu BS'!E16/'SML Isuzu BS'!E38 -> 0.042486562 | E20: ='SML Isuzu BS'!F16/'SML Isuzu BS'!F38 -> 0.0050975113 | F20: ='SML Isuzu BS'!G16/'SML Isuzu BS'!G38 -> 0.017987117
B21: Baseline | C21: 1 | D21: 1 | E21: 1 | F21: 1

Sheet Effectivity Ratio
B3: Days in Receivables (Eicher Motors) | H3: Accounts Receivable Turnover Ratio (ART)
B4: Eicher Motors | C4: March 31, 2025 | D4: March 31, 2024 | E4: March 31, 2023 | F4: March 31, 2022 | H4: Company Name | I4: March 31, 2025 | J4: March 31, 2024 | K4: March 31, 2023 | L4: March 31, 2022
B5: Receivable Turnover Ratio | C5: ='Eicher Motors IS'!D7/'Eicher Motors BS'!D15 -> 36.706299 | D5: ='Eicher Motors IS'!E7/'Eicher Motors BS'!E15 -> 47.11769 | E5: ='Eicher Motors IS'!F7/'Eicher Motors BS'!F15 -> 40.7603 | F5: ='Eicher Motors IS'!G7/'Eicher Motors BS'!G15 -> 35.553735 | H5: Eicher Motors | I5: 36.706299 | J5: 47.11769 | K5: 40.7603 | L5: 35.553735
B6: Days in Receivables | C6: =365/C5 -> 9.9437975 | D6: =365/D5 -> 7.7465598 | E6: =365/E5 -> 8.9547917 | F6: =365/F5 -> 10.266151 | H6: SML Isuzu | I6: 9.0669862 | J6: 13.027811 | K6: 24.089388 | L6: 11.786044
B9: Days in Receivables (SML Isuzu) | H9: Days Sales Outstanding (DSO)
B10: SML Isuzu | C10: March 31, 2025 | D10: March 31, 2024 | E10: March 31, 2023 | F10: March 31, 2022 | H10: Company Name | I10: March 31, 2025 | J10: March 31, 2024 | K10: March 31, 2023 | L10: March 31, 2022
B11: Receivable Turnover Ratio | C11: ='SML Isuzu IS'!D7/'SML Isuzu BS'!D15 -> 9.0669862 | D11: ='SML Isuzu IS'!E7/'SML Isuzu BS'!E15 -> 13.027811 | E11: ='SML Isuzu IS'!F7/'SML Isuzu BS'!F15 -> 24.089388 | F11: ='SML Isuzu IS'!G7/'SML Isuzu BS'!G15 -> 11.786044 | H11: Eicher Motors | I11: 9.9437975 | J11: 7.7465598 | K11: 8.9547917 | L11: 10.266151
B12: Days in Receivables | C12: =365/C11 -> 40.255934 | D12: =365/D11 -> 28.016986 | E12: =365/E11 -> 15.1519 | F12: =365/F11 -> 30.96883 | H12: SML Isuzu | I12: 40.255934 | J12: 28.016986 | K12: 15.1519 | L12: 30.96883
B15: Fixed Asset Turnover Ratio
B16: Company Name | C16: March 31, 2025 | D16: March 31, 2024 | E16: March 31, 2023 | F16: March 31, 2022
B17: Eicher Motors | C17: ='Eicher Motors IS'!D7/'Eicher Motors BS'!D8 -> 8.8928682 | D17: ='Eicher Motors IS'!E7/'Eicher Motors BS'!E8 -> 9.0304113 | E17: ='Eicher Motors IS'!F7/'Eicher Motors BS'!F8 -> 7.519961 | F17: ='Eicher Motors IS'!G7/'Eicher Motors BS'!G8 -> 5.6200348
B18: SML Isuzu | C18: ='SML Isuzu IS'!D7/'SML Isuzu BS'!D8 -> 9.1291705 | D18: ='SML Isuzu IS'!E7/'SML Isuzu BS'!E8 -> 8.2387299 | E18: ='SML Isuzu IS'!F7/'SML Isuzu BS'!F8 -> 6.6277995 | F18: ='SML Isuzu IS'!G7/'SML Isuzu BS'!G8 -> 3.169828
B21: Total Asset Turnover Ratio
B22: Company Name | C22: March 31, 2025 | D22: March 31, 2024 | E22: March 31, 2023 | F22: March 31, 2022
B23: Eicher Motors | C23: ='Eicher Motors IS'!D7/'Eicher Motors BS'!D22 -> 0.74243562 | D23: ='Eicher Motors IS'!E7/'Eicher Motors BS'!E22 -> 0.76148838 | E23: ='Eicher Motors IS'!F7/'Eicher Motors BS'!F22 -> 0.78328847 | F23: ='Eicher Motors IS'!G7/'Eicher Motors BS'!G22 -> 0.66535087
B24: SML Isuzu | C24: ='SML Isuzu IS'!D7/'SML Isuzu BS'!D22 -> 1.8508716 | D24: ='SML Isuzu IS'!E7/'SML Isuzu BS'!E22 -> 1.8155059 | E24: ='SML Isuzu IS'!F7/'SML Isuzu BS'!F22 -> 1.9482986 | F24: ='SML Isuzu IS'!G7/'SML Isuzu BS'!G22 -> 1.1401136

Sheet Profitability Ratio
B3: Operating Profit Margin
B4: Company Name | C4: March 31, 2025 | D4: March 31, 2024 | E4: March 31, 2023 | F4: March 31, 2022
B5: Eicher Motors | C5: ='Eicher Motors IS'!D18/'Eicher Motors IS'!D7 -> 0.26208349 | D5: ='Eicher Motors IS'!E18/'Eicher Motors IS'!E7 -> 0.27284099 | E5: ='Eicher Motors IS'!F18/'Eicher Motors IS'!F7 -> 0.23358464 | F5: ='Eicher Motors IS'!G18/'Eicher Motors IS'!G7 -> 0.20124876
B6: SML Isuzu | C6: ='SML Isuzu IS'!D18/'SML Isuzu IS'!D7 -> 0.079938506 | D6: ='SML Isuzu IS'!E18/'SML Isuzu IS'!E7 -> 0.062143944 | E6: ='SML Isuzu IS'!F18/'SML Isuzu IS'!F7 -> 0.023192612 | F6: ='SML Isuzu IS'!G18/'SML Isuzu IS'!G7 -> -0.084668393
B9: Net Profit Margin
B10: Company Name | C10: March 31, 2025 | D10: March 31, 2024 | E10: March 31, 2023 | F10: March 31, 2022
B11: Eicher Motors | C11: ='Eicher Motors IS'!D27/'Eicher Motors IS'!D7 -> 0.23466574 | D11: ='Eicher Motors IS'!E27/'Eicher Motors IS'!E7 -> 0.22717974 | E11: ='Eicher Motors IS'!F27/'Eicher Motors IS'!F7 -> 0.19378093 | F11: ='Eicher Motors IS'!G27/'Eicher Motors IS'!G7 -> 0.15612763
B12: SML Isuzu | C12: ='SML Isuzu IS'!D27/'SML Isuzu IS'!D7 -> 0.050591294 | D12: ='SML Isuzu IS'!E27/'SML Isuzu IS'!E7 -> 0.049005623 | E12: ='SML Isuzu IS'!F27/'SML Isuzu IS'!F7 -> 0.010870353 | F12: ='SML Isuzu IS'!G27/'SML Isuzu IS'!G7 -> -0.10725397
B15: Return on Equity (ROE)
B16: Company Name | C16: March 31, 2025 | D16: March 31, 2024 | E16: March 31, 2023 | F16: March 31, 2022
B17: Eicher Motors | C17: ='Eicher Motors IS'!D27/'Eicher Motors BS'!D30 -> 0.22231081 | D17: ='Eicher Motors IS'!E27/'Eicher Motors BS'!E30 -> 0.22171751 | E17: ='Eicher Motors IS'!F27/'Eicher Motors BS'!F30 -> 0.19438863 | F17: ='Eicher Motors IS'!G27/'Eicher Motors BS'!G30 -> 0.13297906
B18: SML Isuzu | C18: ='SML Isuzu IS'!D27/'SML Isuzu BS'!D30 -> 0.31796776 | D18: ='SML Isuzu IS'!E27/'SML Isuzu BS'!E30 -> 0.3777389 | E18: ='SML Isuzu IS'!F27/'SML Isuzu BS'!F30 -> 0.11146709 | F18: ='SML Isuzu IS'!G27/'SML Isuzu BS'!G30 -> -0.61776945
B21: Return on Asset (ROA)
B22: Company Name | C22: March 31, 2025 | D22: March 31, 2024 | E22: March 31, 2023 | F22: March 31, 2022
B23: Eicher Motors | C23: ='Eicher Motors IS'!D27/'Eicher Motors BS'!D20 -> 0.17422421 | D23: ='Eicher Motors IS'!E27/'Eicher Motors BS'!E20 -> 0.17299473 | E23: ='Eicher Motors IS'!F27/'Eicher Motors BS'!F20 -> 0.15178637 | F23: ='Eicher Motors IS'!G27/'Eicher Motors BS'!G20 -> 0.10387966
B24: SML Isuzu | C24: ='SML Isuzu IS'!D27/'SML Isuzu BS'!D20 -> 0.093637988 | D24: ='SML Isuzu IS'!E27/'SML Isuzu BS'!E20 -> 0.088969998 | E24: ='SML Isuzu IS'!F27/'SML Isuzu BS'!F20 -> 0.021178694 | F24: ='SML Isuzu IS'!G27/'SML Isuzu BS'!G20 -> -0.12228171
